{"is_source_file": false, "format": "", "description": "", "external_files": [], "external_methods": [], "published": [], "classes": [], "methods": [], "calls": [], "search-terms": [], "state": 2, "file_id": 5, "knowledge_revision": 30, "git_revision": "3d7d8bda8004d4351ace9d4049188fe5c281b9e9", "hash": "318566d13ae3c04631ec0316deecb535", "format-version": 4, "code-base-name": "tic_tac_toe_frontend", "filename": "tic_tac_toe_frontend/README.md", "revision_history": [{"30": "3d7d8bda8004d4351ace9d4049188fe5c281b9e9"}]}